example_package_lorenzomag/__init__.py
example_package_lorenzomag/_version.py
example_package_lorenzomag/data.txt
example_package_lorenzomag/example.py
example_package_lorenzomag-0.0.7.dist-info/LICENSE
example_package_lorenzomag-0.0.7.dist-info/METADATA
example_package_lorenzomag-0.0.7.dist-info/WHEEL
example_package_lorenzomag-0.0.7.dist-info/entry_points.txt
example_package_lorenzomag-0.0.7.dist-info/top_level.txt
example_package_lorenzomag-0.0.7.dist-info/RECORD
