Metadata-Version: 2.1
Name: example_package_lorenzomag
Version: 0.0.7
Summary: A small example package
Author-email: Lorenzo Principe <lorenzomag95@gmail.com>
Requires-Python: >=3.8
License-File: LICENSE
Requires-Dist: numpy
